amulet/zlib/__init__.py
amulet/zlib/__init__.pyi
amulet/zlib/_amulet_zlib.cp312-win_amd64.pyd
amulet/zlib/_amulet_zlib.pyi
amulet/zlib/_version.py
amulet/zlib/amulet_zlib.dll
amulet/zlib/amulet_zlib.lib
amulet/zlib/amulet_zlibConfig.cmake
amulet/zlib/export.hpp
amulet/zlib/py.typed
amulet/zlib/zlib.hpp
amulet/zlib/__pyinstaller/__init__.py
amulet/zlib/__pyinstaller/hook-amulet.zlib.py
amulet_zlib-1.0.8a3.dist-info/licenses/LICENSE
amulet_zlib-1.0.8a3.dist-info/METADATA
amulet_zlib-1.0.8a3.dist-info/WHEEL
amulet_zlib-1.0.8a3.dist-info/entry_points.txt
amulet_zlib-1.0.8a3.dist-info/top_level.txt
amulet_zlib-1.0.8a3.dist-info/RECORD
