Metadata-Version: 2.4
Name: amulet-zlib
Version: 1.0.8a3
Summary: A Python and C++ wrapper around zlib.
Author: James Clare
Project-URL: Homepage, https://www.amuletmc.com
Project-URL: Repository, https://github.com/Amulet-Team/Amulet-zlib
Project-URL: Issues, https://github.com/Amulet-Team/Amulet-zlib/issues
Classifier: Programming Language :: Python :: 3
Classifier: Operating System :: OS Independent
Requires-Python: >=3.11
License-File: LICENSE
Requires-Dist: amulet-compiler-target==2.0
Requires-Dist: amulet-compiler-version==4.1297307203.19
Requires-Dist: pybind11==3.0.0
Requires-Dist: amulet-pybind11-extensions~=1.2.0.0a2
Provides-Extra: docs
Requires-Dist: Sphinx>=1.7.4; extra == "docs"
Requires-Dist: sphinx-autodoc-typehints>=1.3.0; extra == "docs"
Requires-Dist: sphinx_rtd_theme>=0.3.1; extra == "docs"
Provides-Extra: dev
Requires-Dist: setuptools>=42; extra == "dev"
Requires-Dist: versioneer; extra == "dev"
Requires-Dist: packaging; extra == "dev"
Requires-Dist: wheel; extra == "dev"
Requires-Dist: pybind11_stubgen>=2.5.4; extra == "dev"
Requires-Dist: black>=22.3; extra == "dev"
Requires-Dist: isort; extra == "dev"
Requires-Dist: autoflake; extra == "dev"
Requires-Dist: mypy; extra == "dev"
Requires-Dist: types-pyinstaller; extra == "dev"
Requires-Dist: amulet-test-utils~=1.3; extra == "dev"
Dynamic: license-file
Dynamic: requires-dist
